ealpython_reader_onopriienko-1.1.4.dist-info/licenses/LICENSE
reader/__init__.py
reader/__main__.py
reader/config.toml
reader/feed.py
reader/viewer.py
ealpython_reader_onopriienko-1.1.4.dist-info/METADATA
ealpython_reader_onopriienko-1.1.4.dist-info/WHEEL
ealpython_reader_onopriienko-1.1.4.dist-info/entry_points.txt
ealpython_reader_onopriienko-1.1.4.dist-info/top_level.txt
ealpython_reader_onopriienko-1.1.4.dist-info/RECORD
